{
  "lastUpdate": "2023-04-09T02:29:26Z",
  "departures": [
    {
      "id": "T111R10410",
      "delayInSeconds": 253,
      "estimatedTime": "2023-04-09T02:36:13Z",
      "headsign": "Kacze Buki",
      "routeId": 10410,
      "scheduledTripStartTime": "2023-04-09T02:09:00Z",
      "tripId": 111,
      "status": "REALTIME",
      "theoreticalTime": "2023-04-09T02:32:00Z",
      "timestamp": "2023-04-09T02:29:19Z",
      "trip": 5267391,
      "vehicleCode": 2082,
      "vehicleId": 1318,
      "vehicleService": "410-06"
    },
    {
      "id": "T251R10282",
      "delayInSeconds": null,
      "estimatedTime": "2023-04-09T02:57:00Z",
      "headsign": "Dom Marynarza",
      "routeId": 10282,
      "scheduledTripStartTime": "2023-04-09T02:36:00Z",
      "tripId": 251,
      "status": "SCHEDULED",
      "theoreticalTime": "2023-04-09T02:57:00Z",
      "timestamp": "2023-04-09T02:29:27Z",
      "trip": 5268550,
      "vehicleCode": null,
      "vehicleId": null,
      "vehicleService": "282-01"
    },
    {
      "id": "T51R10741",
      "delayInSeconds": null,
      "estimatedTime": "2023-04-09T02:58:00Z",
      "headsign": "Gdynia Dworzec Gł",
      "routeId": 10741,
      "scheduledTripStartTime": "2023-04-09T02:49:00Z",
      "tripId": 51,
      "status": "SCHEDULED",
      "theoreticalTime": "2023-04-09T02:58:00Z",
      "timestamp": "2023-04-09T02:29:27Z",
      "trip": 5266827,
      "vehicleCode": null,
      "vehicleId": null,
      "vehicleService": "150-02"
    },
    {
      "id": "T191R10032",
      "delayInSeconds": null,
      "estimatedTime": "2023-04-09T03:08:00Z",
      "headsign": "Mały Kack Sandomi",
      "routeId": 10032,
      "scheduledTripStartTime": "2023-04-09T03:06:00Z",
      "tripId": 191,
      "status": "SCHEDULED",
      "theoreticalTime": "2023-04-09T03:08:00Z",
      "timestamp": "2023-04-09T02:29:27Z",
      "trip": 5265325,
      "vehicleCode": null,
      "vehicleId": null,
      "vehicleService": "032-01"
    },
    {
      "id": "T401R10150",
      "delayInSeconds": null,
      "estimatedTime": "2023-04-09T03:15:00Z",
      "headsign": "Witomino Leśniczó",
      "routeId": 10150,
      "scheduledTripStartTime": "2023-04-09T02:57:00Z",
      "tripId": 401,
      "status": "SCHEDULED",
      "theoreticalTime": "2023-04-09T03:15:00Z",
      "timestamp": "2023-04-09T02:29:27Z",
      "trip": 5265928,
      "vehicleCode": null,
      "vehicleId": null,
      "vehicleService": "150-03"
    },
    {
      "id": "T251R10282",
      "delayInSeconds": null,
      "estimatedTime": "2023-04-09T03:17:00Z",
      "headsign": "Dom Marynarza",
      "routeId": 10282,
      "scheduledTripStartTime": "2023-04-09T02:56:00Z",
      "tripId": 251,
      "status": "SCHEDULED",
      "theoreticalTime": "2023-04-09T03:17:00Z",
      "timestamp": "2023-04-09T02:29:27Z",
      "trip": 5266473,
      "vehicleCode": null,
      "vehicleId": null,
      "vehicleService": "282-02"
    },
    {
      "id": "T11R10146",
      "delayInSeconds": null,
      "estimatedTime": "2023-04-09T03:22:00Z",
      "headsign": "Plac Kaszubski",
      "routeId": 10146,
      "scheduledTripStartTime": "2023-04-09T02:45:00Z",
      "tripId": 11,
      "status": "SCHEDULED",
      "theoreticalTime": "2023-04-09T03:22:00Z",
      "timestamp": "2023-04-09T02:29:27Z",
      "trip": 5268183,
      "vehicleCode": null,
      "vehicleId": null,
      "vehicleService": "146-01"
    },
    {
      "id": "T281R10194",
      "delayInSeconds": null,
      "estimatedTime": "2023-04-09T03:27:00Z",
      "headsign": "Plac Kaszubski",
      "routeId": 10194,
      "scheduledTripStartTime": "2023-04-09T03:13:00Z",
      "tripId": 281,
      "status": "SCHEDULED",
      "theoreticalTime": "2023-04-09T03:27:00Z",
      "timestamp": "2023-04-09T02:29:27Z",
      "trip": 5266303,
      "vehicleCode": null,
      "vehicleId": null,
      "vehicleService": "194-01"
    },
    {
      "id": "T191R10032",
      "delayInSeconds": null,
      "estimatedTime": "2023-04-09T03:38:00Z",
      "headsign": "Mały Kack Sandomi",
      "routeId": 10032,
      "scheduledTripStartTime": "2023-04-09T03:36:00Z",
      "tripId": 191,
      "status": "SCHEDULED",
      "theoreticalTime": "2023-04-09T03:38:00Z",
      "timestamp": "2023-04-09T02:29:27Z",
      "trip": 5265348,
      "vehicleCode": null,
      "vehicleId": null,
      "vehicleService": "032-02"
    },
    {
      "id": "T251R10282",
      "delayInSeconds": null,
      "estimatedTime": "2023-04-09T03:47:00Z",
      "headsign": "Dom Marynarza",
      "routeId": 10282,
      "scheduledTripStartTime": "2023-04-09T03:26:00Z",
      "tripId": 251,
      "status": "SCHEDULED",
      "theoreticalTime": "2023-04-09T03:47:00Z",
      "timestamp": "2023-04-09T02:29:27Z",
      "trip": 5266495,
      "vehicleCode": null,
      "vehicleId": null,
      "vehicleService": "282-04"
    },
    {
      "id": "T401R10150",
      "delayInSeconds": null,
      "estimatedTime": "2023-04-09T03:50:00Z",
      "headsign": "Witomino Leśniczó",
      "routeId": 10150,
      "scheduledTripStartTime": "2023-04-09T03:32:00Z",
      "tripId": 401,
      "status": "SCHEDULED",
      "theoreticalTime": "2023-04-09T03:50:00Z",
      "timestamp": "2023-04-09T02:29:27Z",
      "trip": 5265944,
      "vehicleCode": null,
      "vehicleId": null,
      "vehicleService": "150-04"
    },
    {
      "id": "T31R10173",
      "delayInSeconds": null,
      "estimatedTime": "2023-04-09T03:51:00Z",
      "headsign": "Plac Kaszubski",
      "routeId": 10173,
      "scheduledTripStartTime": "2023-04-09T02:53:00Z",
      "tripId": 31,
      "status": "SCHEDULED",
      "theoreticalTime": "2023-04-09T03:51:00Z",
      "timestamp": "2023-04-09T02:29:27Z",
      "trip": 5268607,
      "vehicleCode": null,
      "vehicleId": null,
      "vehicleService": "173-20"
    },
    {
      "id": "T281R10194",
      "delayInSeconds": null,
      "estimatedTime": "2023-04-09T03:57:00Z",
      "headsign": "Plac Kaszubski",
      "routeId": 10194,
      "scheduledTripStartTime": "2023-04-09T03:43:00Z",
      "tripId": 281,
      "status": "SCHEDULED",
      "theoreticalTime": "2023-04-09T03:57:00Z",
      "timestamp": "2023-04-09T02:29:27Z",
      "trip": 5266329,
      "vehicleCode": null,
      "vehicleId": null,
      "vehicleService": "194-02"
    }
  ]
}